baopig/__init__.py
baopig/communicative.py
baopig/documentation.py
baopig/lines_counter.py
baopig/__pycache__/__init__.cpython-310.pyc
baopig/__pycache__/__init__.cpython-311.pyc
baopig/__pycache__/__init__.cpython-37.pyc
baopig/__pycache__/communicative.cpython-310.pyc
baopig/__pycache__/communicative.cpython-311.pyc
baopig/__pycache__/communicative.cpython-37.pyc
baopig/__pycache__/documentation.cpython-310.pyc
baopig/__pycache__/documentation.cpython-311.pyc
baopig/font/__init__.py
baopig/font/font.py
baopig/font/__pycache__/__init__.cpython-310.pyc
baopig/font/__pycache__/__init__.cpython-311.pyc
baopig/font/__pycache__/__init__.cpython-37.pyc
baopig/font/__pycache__/font.cpython-310.pyc
baopig/font/__pycache__/font.cpython-311.pyc
baopig/font/lib/JetBrainsMono-1.0.2/ttf/JetBrainsMono-Bold-Italic.ttf
baopig/font/lib/JetBrainsMono-1.0.2/ttf/JetBrainsMono-Bold.ttf
baopig/font/lib/JetBrainsMono-1.0.2/ttf/JetBrainsMono-ExtraBold-Italic.ttf
baopig/font/lib/JetBrainsMono-1.0.2/ttf/JetBrainsMono-ExtraBold.ttf
baopig/font/lib/JetBrainsMono-1.0.2/ttf/JetBrainsMono-Italic.ttf
baopig/font/lib/JetBrainsMono-1.0.2/ttf/JetBrainsMono-Medium-Italic.ttf
baopig/font/lib/JetBrainsMono-1.0.2/ttf/JetBrainsMono-Medium.ttf
baopig/font/lib/JetBrainsMono-1.0.2/ttf/JetBrainsMono-Regular.ttf
baopig/font/lib/JetBrainsMono-1.0.2/web/eot/JetBrainsMono-Bold-Italic.eot
baopig/font/lib/JetBrainsMono-1.0.2/web/eot/JetBrainsMono-Bold.eot
baopig/font/lib/JetBrainsMono-1.0.2/web/eot/JetBrainsMono-ExtraBold-Italic.eot
baopig/font/lib/JetBrainsMono-1.0.2/web/eot/JetBrainsMono-ExtraBold.eot
baopig/font/lib/JetBrainsMono-1.0.2/web/eot/JetBrainsMono-Italic.eot
baopig/font/lib/JetBrainsMono-1.0.2/web/eot/JetBrainsMono-Medium-Italic.eot
baopig/font/lib/JetBrainsMono-1.0.2/web/eot/JetBrainsMono-Medium.eot
baopig/font/lib/JetBrainsMono-1.0.2/web/eot/JetBrainsMono-Regular.eot
baopig/font/lib/JetBrainsMono-1.0.2/web/woff/JetBrainsMono-Bold-Italic.woff
baopig-0.20.6.dist-info/LICENSE
baopig-0.20.6.dist-info/METADATA
baopig-0.20.6.dist-info/WHEEL
baopig-0.20.6.dist-info/top_level.txt
baopig-0.20.6.dist-info/RECORD
