Metadata-Version: 2.1
Name: baopig
Version: 0.20.6
Summary: pygame gui
Home-page: https://baopig.readthedocs.io/
Author: Symeon Rougevin-Baville
Author-email: dev.chresyr@gmail.com
License: MIT
Classifier: Intended Audience :: Developers
Classifier: License :: OSI Approved :: MIT License
Classifier: Programming Language :: Python
Classifier: Programming Language :: Python :: 3
Classifier: Programming Language :: Python :: 3.6
Classifier: Programming Language :: Python :: 3.7
Classifier: Programming Language :: Python :: 3.8
Classifier: Programming Language :: Python :: 3.9
Classifier: Operating System :: OS Independent
License-File: LICENSE
Requires-Dist: pygame
Requires-Dist: httpcore
Requires-Dist: httpx[http2]
